[
    {
        "event_id": "2775770",
        "start_time": "2026-02-07 22:30:00",
        "league": "Bundesliga - Germany",
        "host_team": "1. FC Heidenheim",
        "visit_team": "Hamburger SV",
        "num": "周六001",
        "odds_3": "3.4",
        "odds_1": "2.54",
        "odds_0": "2.69",
        "status": "未开始",
        "ai_prediction": "分析中",
        "ai_analysis": "数据获取超时，请关注临场指数变化。"
    },
    {
        "event_id": "2387267",
        "start_time": "2026-02-07 22:30:00",
        "league": "Bundesliga - Germany",
        "host_team": "FSV Mainz 05",
        "visit_team": "Augsburg",
        "num": "周六002",
        "odds_3": "1.42",
        "odds_1": "4.07",
        "odds_0": "9.2",
        "status": "未开始",
        "ai_prediction": "分析中",
        "ai_analysis": "数据获取超时，请关注临场指数变化。"
    },
    {
        "event_id": "10868346",
        "start_time": "2026-02-07 22:30:00",
        "league": "Bundesliga - Germany",
        "host_team": "VfL Wolfsburg",
        "visit_team": "Borussia Dortmund",
        "num": "周六003",
        "odds_3": "12.28",
        "odds_1": "5.34",
        "odds_0": "1.27",
        "status": "未开始",
        "ai_prediction": "分析中",
        "ai_analysis": "数据获取超时，请关注临场指数变化。"
    },
    {
        "event_id": "9406158",
        "start_time": "2026-02-07 22:30:00",
        "league": "Bundesliga - Germany",
        "host_team": "FC St. Pauli",
        "visit_team": "VfB Stuttgart",
        "num": "周六004",
        "odds_3": "2.1",
        "odds_1": "3.01",
        "odds_0": "4.0",
        "status": "未开始",
        "ai_prediction": "分析中",
        "ai_analysis": "数据获取超时，请关注临场指数变化。"
    },
    {
        "event_id": "6103091",
        "start_time": "2026-02-07 22:30:00",
        "league": "Bundesliga - Germany",
        "host_team": "SC Freiburg",
        "visit_team": "Werder Bremen",
        "num": "周六005",
        "odds_3": "1.45",
        "odds_1": "3.87",
        "odds_0": "8.89",
        "status": "未开始",
        "ai_prediction": "分析中",
        "ai_analysis": "数据获取超时，请关注临场指数变化。"
    },
    {
        "event_id": "7292602",
        "start_time": "2026-02-07 23:15:00",
        "league": "La Liga - Spain",
        "host_team": "Barcelona",
        "visit_team": "Mallorca",
        "num": "周六006",
        "odds_3": "1.15",
        "odds_1": "8.0",
        "odds_0": "13.0",
        "status": "未开始",
        "ai_prediction": "分析中",
        "ai_analysis": "数据获取超时，请关注临场指数变化。"
    },
    {
        "event_id": "8466523",
        "start_time": "2026-02-07 23:15:00",
        "league": "La Liga 2 - Spain",
        "host_team": "Las Palmas",
        "visit_team": "Burgos CF",
        "num": "周六007",
        "odds_3": "1.89",
        "odds_1": "2.75",
        "odds_0": "4.75",
        "status": "未开始",
        "ai_prediction": "分析中",
        "ai_analysis": "数据获取超时，请关注临场指数变化。"
    },
    {
        "event_id": "3418212",
        "start_time": "2026-02-08 00:00:00",
        "league": "Austrian Football Bundesliga",
        "host_team": "Rapid Wien",
        "visit_team": "Hartberg",
        "num": "周日008",
        "odds_3": "1.85",
        "odds_1": "3.3",
        "odds_0": "4.0",
        "status": "未开始",
        "ai_prediction": "分析中",
        "ai_analysis": "数据获取超时，请关注临场指数变化。"
    },
    {
        "event_id": "2394224",
        "start_time": "2026-02-08 00:00:00",
        "league": "Austrian Football Bundesliga",
        "host_team": "LASK",
        "visit_team": "WSG Tirol",
        "num": "周日009",
        "odds_3": "1.65",
        "odds_1": "3.6",
        "odds_0": "5.0",
        "status": "未开始",
        "ai_prediction": "分析中",
        "ai_analysis": "数据获取超时，请关注临场指数变化。"
    },
    {
        "event_id": "8969164",
        "start_time": "2026-02-08 00:00:00",
        "league": "Ligue 1 - France",
        "host_team": "RC Lens",
        "visit_team": "Rennes",
        "num": "周日010",
        "odds_3": "1.55",
        "odds_1": "4.0",
        "odds_0": "5.5",
        "status": "未开始",
        "ai_prediction": "分析中",
        "ai_analysis": "数据获取超时，请关注临场指数变化。"
    }
]