[
    {
        "event_id": "4408824",
        "start_time": "2026-02-07 11:11:29",
        "league": "NBA",
        "host_team": "Portland Trail Blazers",
        "visit_team": "Memphis Grizzlies",
        "num": "周六001",
        "odds_3": "1.15",
        "odds_1": "0.00",
        "odds_0": "6.03",
        "status": "未开始",
        "ai_prediction": "分析中",
        "ai_analysis": "数据获取超时，请关注临场指数变化。"
    },
    {
        "event_id": "6062945",
        "start_time": "2026-02-07 11:12:00",
        "league": "NBA",
        "host_team": "Sacramento Kings",
        "visit_team": "Los Angeles Clippers",
        "num": "周六002",
        "odds_3": "2.9",
        "odds_1": "0.00",
        "odds_0": "1.41",
        "status": "未开始",
        "ai_prediction": "分析中",
        "ai_analysis": "数据获取超时，请关注临场指数变化。"
    },
    {
        "event_id": "3110269",
        "start_time": "2026-02-07 14:36:00",
        "league": "NBL",
        "host_team": "New Zealand Breakers",
        "visit_team": "Illawarra Hawks",
        "num": "周六003",
        "odds_3": "2.8",
        "odds_1": "0.00",
        "odds_0": "1.43",
        "status": "未开始",
        "ai_prediction": "分析中",
        "ai_analysis": "数据获取超时，请关注临场指数变化。"
    }
]