[
    {
        "event_id": "8188970",
        "start_time": "2025-12-27 08:10:00",
        "league": "NBA",
        "host_team": "Atlanta Hawks",
        "visit_team": "Miami Heat",
        "num": "周六001",
        "odds_3": "1.67",
        "odds_1": "0.00",
        "odds_0": "2.2",
        "status": "未开始",
        "ai_prediction": "主胜",
        "ai_analysis": "亚特兰大老鹰坐镇State Farm球馆，进攻端的运转明显比客场更加流畅。特雷·杨作为持球大核，其挡拆发起的威胁能有效撕扯热火引以为傲的联防体系，尤其是在内线吃饼效率在线的情况下，热火核心阿德巴约将面临巨大的协防压力，难以兼顾护框与外线扫荡。迈阿密热火本赛季在客场的进攻延续性一直是个老大难问题，虽然巴特勒的硬解能力毋庸置疑，但球队整体外线投射的不稳定性往往导致他们在追分阶段显得力不从心。加上老鹰主场以逸待劳，体能优势在第四节会被放大。只要老鹰不陷入单打独斗的怪圈，利用快节奏转换拖垮热火的阵地战防守，主场拿下比赛的概率极高。"
    },
    {
        "event_id": "10028315",
        "start_time": "2025-12-27 08:10:00",
        "league": "NBA",
        "host_team": "Indiana Pacers",
        "visit_team": "Boston Celtics",
        "num": "周六002",
        "odds_3": "3.6",
        "odds_1": "0.00",
        "odds_0": "1.29",
        "status": "未开始",
        "ai_prediction": "客胜",
        "ai_analysis": "印第安纳步行者引以为傲的跑轰体系今晚将面临严峻考验，虽然哈利伯顿的组织能带动主场节奏，但球队羸弱的防守端在面对凯尔特人这种顶级锋线群时显得捉襟见肘。波士顿的双探花塔图姆和布朗具备极强的单点爆破能力，能够轻易撕裂步行者缺乏护框的内线防线。更关键的是，凯尔特人拥有联盟顶级的无限换防资源，这会极大限制步行者依赖的挡拆进攻效率。即便坐拥主场之利，若无法在三分线外投出超高命中率，步行者很难弥补双方在攻防纪律性上的巨大鸿沟，绿军的阵容深度和战术执行力显然更胜一筹。"
    },
    {
        "event_id": "6580243",
        "start_time": "2025-12-27 08:10:00",
        "league": "NBA",
        "host_team": "Orlando Magic",
        "visit_team": "Charlotte Hornets",
        "num": "周六003",
        "odds_3": "1.4",
        "odds_1": "0.00",
        "odds_0": "2.9",
        "status": "未开始",
        "ai_prediction": "主胜",
        "ai_analysis": "奥兰多魔术本赛季的防守体系已经完全成型，尤其是在主场，他们利用锋线群的身高臂展构建了极具压迫感的防守网。面对夏洛特黄蜂这种极度依赖外线手感和转换进攻节奏的球队，魔术的战术纪律性是最大的克制武器。黄蜂队虽然在进攻端偶有爆发力，但内线护框能力一直是致命硬伤，这将导致他们在禁区内被魔术的高大锋线轮番冲击，很难保护住后场篮板。\n\n此外，黄蜂的客场抗压能力较弱，一旦比赛陷入阵地战泥潭，他们缺乏能够硬解高强度防守的手段。魔术只要控制住失误，利用体型优势在内线制造杀伤并冲抢前场篮板，就能在节奏上完全压制对手。这场比赛不仅是天赋的对抗，更是战术素养的较量，魔术在攻防两端的稳定性显然更胜一筹。"
    },
    {
        "event_id": "10526530",
        "start_time": "2025-12-27 08:10:00",
        "league": "NBA",
        "host_team": "Washington Wizards",
        "visit_team": "Toronto Raptors",
        "num": "周六004",
        "odds_3": "3.5",
        "odds_1": "0.00",
        "odds_0": "1.3",
        "status": "未开始",
        "ai_prediction": "客胜",
        "ai_analysis": "华盛顿奇才目前的防守体系形同虚设，内线护框能力的缺失让对手在禁区予取予求。尽管坐镇主场，但球队缺乏稳定的战术纪律，核心球员往往陷入低效的单打独斗，难以弥补整体攻防的严重脱节。反观多伦多猛龙，虽然处于阵容调整期，但其锋线群在运动能力和对抗强度上完全碾压对手。猛龙擅长的转换进攻将极大惩罚奇才的高失误率，且客队在战术执行力和防守韧性上远胜主队。奇才这种松散的防守态度很难在主场抵挡住猛龙更有针对性的冲击，双方硬实力存在明显断层，猛龙客场带走胜利是大概率事件。"
    },
    {
        "event_id": "11554209",
        "start_time": "2025-12-27 08:40:00",
        "league": "NBA",
        "host_team": "Chicago Bulls",
        "visit_team": "Philadelphia 76ers",
        "num": "周六005",
        "odds_3": "2.0",
        "odds_1": "0.00",
        "odds_0": "1.83",
        "status": "未开始",
        "ai_prediction": "客胜",
        "ai_analysis": "芝加哥公牛近期攻防两端极度缺乏稳定性，尤其在限制对手内线得分方面存在天然短板。武切维奇在面对费城具有统治力的内线时，横移速度和护框能力的劣势往往会被无限放大，这将迫使公牛频繁收缩防线，从而漏给76人外线射手群大量空位机会。费城方面，马克西的持球推进速度能有效撕扯公牛脆弱的转换防守，即便客场作战，他们在阵地战的战术执行力和球星硬解能力上也远胜主队。公牛若想守住联合中心，必须依赖极高效率的单打和三分爆种，但面对费城严密的防守体系，这种容错率太低。硬实力层面的差距，注定客队将掌控比赛走势。"
    },
    {
        "event_id": "8791365",
        "start_time": "2025-12-27 09:00:00",
        "league": "NBA",
        "host_team": "New Orleans Pelicans",
        "visit_team": "Phoenix Suns",
        "num": "周六006",
        "odds_3": "2.66",
        "odds_1": "0.00",
        "odds_0": "1.54",
        "status": "未开始",
        "ai_prediction": "客胜",
        "ai_analysis": "鹈鹕目前的阵容结构在面对拥有顶级单打手的球队时显得捉襟见肘。球队近期在防守端轮转迟缓，若无法在内线制造绝对杀伤，便不得不陷入与太阳进行中远投对攻的陷阱，这恰恰是菲尼克斯最擅长的领域。太阳队杜兰特与布克在关键时刻的硬解能力远在鹈鹕之上，这种球星成色在胶着时刻往往是决定性的。尽管新奥尔良拥有主场加持，但侧翼防守资源的匮乏让他们很难限制太阳的多点开花。只要太阳不出现断崖式的手感冰凉，鹈鹕很难在四节比赛中始终咬住比分，客队在进攻端的容错率明显更高。"
    },
    {
        "event_id": "10926809",
        "start_time": "2025-12-27 09:10:00",
        "league": "NBA",
        "host_team": "Memphis Grizzlies",
        "visit_team": "Milwaukee Bucks",
        "num": "周六007",
        "odds_3": "1.44",
        "odds_1": "0.00",
        "odds_0": "2.75",
        "status": "未开始",
        "ai_prediction": "主胜",
        "ai_analysis": "灰熊坐镇联邦快递球馆，近期展现出的攻防转换速度令人窒息。球队在内线的护框与篮板拼抢上硬度十足，这为他们标志性的反击奠定了基础。面对雄鹿，灰熊的策略非常明确：利用年轻化的阵容不断提速，坚决冲击对手相对老化的防守核心。雄鹿近期客场表现疲软，防守端沟通严重脱节，尤其是退防速度难以匹配灰熊的冲击力。若无法有效限制灰熊的禁区得分，雄鹿单纯依靠外线投射很难在客场全身而退。结合主场气势与体能优势，孟菲斯人显然握有比赛的主动权。"
    }
]