[
    {
        "event_id": "7430583",
        "start_time": "2026-01-04 22:00:00",
        "league": "Serie A - Italy",
        "host_team": "Fiorentina",
        "visit_team": "Cremonese",
        "num": "周日001",
        "odds_3": "1.84",
        "odds_1": "2.76",
        "odds_0": "6.39",
        "status": "未开始",
        "ai_prediction": "主胜",
        "ai_analysis": "紫百合坐镇弗兰基球场，面对实力有限的克雷莫纳，这不仅仅是一场普通的较量，更是检验球队攻坚能力的试金石。虽然2.76的超低平赔预示着客队将采取极致的防守反击策略，试图通过密集防守将比赛拖入泥潭，但佛罗伦萨在中前场的控制力以及边路突击的战术素养，足以撕开对手的防线。作为意甲老牌劲旅，他们在主场的战术执行力和底蕴远非克雷莫纳可比。克雷莫纳客场作战往往缺乏韧性，且阵容深度难以支撑90分钟的高强度抗压。1.84的主胜赔率在合理区间，既规避了过热风险，又给予了主队足够的支持，紫百合全取三分是正路。"
    },
    {
        "event_id": "3482099",
        "start_time": "2026-01-04 22:01:00",
        "league": "Ligue 1 - France",
        "host_team": "Marseille",
        "visit_team": "Nantes",
        "num": "周日002",
        "odds_3": "7.26",
        "odds_1": "3.81",
        "odds_0": "1.48",
        "status": "未开始",
        "ai_prediction": "客胜",
        "ai_analysis": "马赛近期防线的崩盘简直是灾难级的，韦洛德罗姆球场曾经的威慑力在连续的战术混乱中已荡然无存。球队目前中后场脱节严重，面对南特这种以快速反击和高位逼抢见长的球队，马赛笨重的后防线将暴露无遗。南特方面，虽然客场作战，但他们的战术执行力远在主队之上，锋线把握机会的能力极其高效，且全员健康度优于对手。在马赛多名核心球员状态低迷且更衣室氛围微妙的情况下，即便坐拥主场之利也难掩颓势。南特只要正常发挥其在中场的硬度优势，利用对手急于进攻留下的身后空档，带走三分几乎是板上钉钉。"
    },
    {
        "event_id": "9083434",
        "start_time": "2026-01-04 23:15:00",
        "league": "La Liga 2 - Spain",
        "host_team": "AD Ceuta FC",
        "visit_team": "Andorra CF",
        "num": "周日003",
        "odds_3": "2.03",
        "odds_1": "3.49",
        "odds_0": "3.92",
        "status": "未开始",
        "ai_prediction": "主胜",
        "ai_analysis": "AD Ceuta FC 坐镇阿方索·穆鲁贝球场展现出的统治力令人窒息，这支球队在北非飞地的特殊主场氛围加持下，往往能爆发出远超账面实力的战斗意志，尤其在中前场的绞杀硬度上极具侵略性。相比之下，Andorra CF 虽然坚持传控体系，但在客场面对高强度逼抢时，后场出球的抗压能力不足，且锋线缺乏一锤定音的终结者，极易陷入“得势不得分”的困境。两队球风存在明显的克制关系，Ceuta 的硬朗与直接正好击中 Andorra 偏软的软肋。考虑到客队远征的舟车劳顿以及主队在转换进攻端的高效，Andorra 很难抵挡主队的冲击，Ceuta 全取三分的战术逻辑非常清晰。"
    },
    {
        "event_id": "10809478",
        "start_time": "2026-01-04 23:15:00",
        "league": "La Liga - Spain",
        "host_team": "Real Madrid",
        "visit_team": "Real Betis",
        "num": "周日004",
        "odds_3": "1.44",
        "odds_1": "4.4",
        "odds_0": "6.0",
        "status": "未开始",
        "ai_prediction": "主胜",
        "ai_analysis": "皇马坐镇伯纳乌，这不仅仅是主场优势，更是一种心理压制。安切洛蒂的球队近期展现出了极高的战术弹性，尤其是在攻守转换的瞬间，锋线球员的速度将是撕开贝蒂斯防线的利刃。尽管贝蒂斯在佩莱格里尼的调教下具备不俗的控球能力，但他们在中后场的抗压能力面对顶级豪门时往往显得捉襟见肘，一旦阵型压上，身后巨大的空档无异于给皇马送分。此外，皇马中场的硬度与控制力足以切断贝蒂斯的反击源头，只要银河战舰保持专注，不出现严重的防守失误，客队很难在马德里全身而退。贝蒂斯或许能制造零星威胁，但很难抵挡皇马全场的高压攻势。"
    },
    {
        "event_id": "4925163",
        "start_time": "2026-01-05 00:00:00",
        "league": "Africa Cup of Nations",
        "host_team": "Morocco",
        "visit_team": "Tanzania",
        "num": "周一005",
        "odds_3": "1.12",
        "odds_1": "8.0",
        "odds_0": "23.0",
        "status": "未开始",
        "ai_prediction": "主胜",
        "ai_analysis": "摩洛哥作为世界杯四强球队，其阵容厚度在非洲大陆堪称降维打击。阿什拉夫与齐耶赫组成的右路走廊是撕裂防线的核武器，面对坦桑尼亚这种缺乏顶级联赛防守经验的球队，摩洛哥的高位压迫将迫使对手在自家半场频繁丢球。坦桑尼亚虽然在预选赛表现顽强，但整体技战术素养与北非劲旅存在档次上的差距，他们的单兵防守能力很难在90分钟内持续限制住恩内斯里的抢点和欧纳希的后插上。尽管非洲杯赛场往往充满变数，且坦桑尼亚势必摆出铁桶阵死守，但摩洛哥只要保持耐心，利用定位球和边路爆破尽早打破僵局，这场比赛极大概率将演变成半场攻防演练。双方硬实力悬殊过大，爆冷空间几乎被压缩殆尽。"
    },
    {
        "event_id": "3508269",
        "start_time": "2026-01-05 00:15:00",
        "league": "Ligue 1 - France",
        "host_team": "Le Havre",
        "visit_team": "Angers",
        "num": "周一006",
        "odds_3": "2.1",
        "odds_1": "3.1",
        "odds_0": "3.4",
        "status": "未开始",
        "ai_prediction": "主胜",
        "ai_analysis": "勒阿弗尔坐镇奥赛恩球场，这场法甲保级序列的直接对话，主队占据了心理与地利的双重优势。虽然球队近期运动战进球效率一般，但其主场防守体系的层次感远胜昂热，尤其是对肋部的保护做得相当到位。昂热作为典型的“客场虫”，最大的软肋在于中场失控后的防线退守速度过慢，且缺乏能在僵局中一锤定音的爆点球员。在法甲这种强调身体对抗的节奏中，勒阿弗尔更硬朗的球风足以压制昂热的传控尝试。考虑到昂热客场疲软的攻防转换效率，只要勒阿弗尔稳扎稳打，利用主场气势抢开局，大概率能通过实用主义足球拿下这场关键战役。"
    },
    {
        "event_id": "10736278",
        "start_time": "2026-01-05 00:15:00",
        "league": "Ligue 1 - France",
        "host_team": "Brest",
        "visit_team": "Auxerre",
        "num": "周一007",
        "odds_3": "1.85",
        "odds_1": "3.25",
        "odds_0": "4.0",
        "status": "未开始",
        "ai_prediction": "主胜",
        "ai_analysis": "布雷斯特虽然近期受欧战赛程牵扯，体能略显吃紧，但弗朗西斯-勒布雷球场依然是法甲最难攻克的堡垒之一。埃里克·罗伊的战术体系极具侵略性，特别是边路德尔·卡斯蒂略发起的攻势，对于欧塞尔这种防守肋部空档能力较弱的球队是致命打击。反观欧塞尔，作为升班马在客场显得水土不服，中场缺乏硬度导致防线长期暴露在火力之下，且球队极度依赖反击运气。在主队急需联赛抢分稳固排名的背景下，欧塞尔孱弱的客场抗压能力恐难全身而退，双方在攻防转换速率上的差距将决定比赛走势。"
    },
    {
        "event_id": "11497328",
        "start_time": "2026-01-05 00:15:00",
        "league": "Ligue 1 - France",
        "host_team": "Lorient",
        "visit_team": "Metz",
        "num": "周一008",
        "odds_3": "1.8",
        "odds_1": "3.4",
        "odds_0": "4.2",
        "status": "未开始",
        "ai_prediction": "主胜",
        "ai_analysis": "洛里昂坐镇穆斯托伊尔球场往往能展现出截然不同的精神面貌，近期球队在攻守转换的速率上有了显著提升，特别是利用主场优势进行的边路突击，将极大考验梅斯薄弱的肋部防守。梅斯本赛季“客场虫”的属性难以改变，中场缺乏硬度导致防线频繁暴露，且在面对高位逼抢时出球困难，一旦先丢球极易陷入崩盘节奏。虽然客队有保级抢分的战意，但技战术执行力的匮乏让他们在逆风局中往往毫无还手之力。洛里昂目前阵容相对齐整，只要避免后防低级失误，凭借更胜一筹的进攻效率和主场气势，拿下这场关键战役不成问题。"
    }
]